LICENSE
MANIFEST.in
README.rst
pavement.py
requirements-dev.txt
requirements.txt
setup.py
tox.ini
btsbots/BTSBotsClient.py
btsbots/DDPClient.py
btsbots/MeteorClient.py
btsbots/TradeBots.py
btsbots/__init__.py
btsbots/main.py
btsbots/metadata.py
btsbots.egg-info/PKG-INFO
btsbots.egg-info/SOURCES.txt
btsbots.egg-info/dependency_links.txt
btsbots.egg-info/entry_points.txt
btsbots.egg-info/not-zip-safe
btsbots.egg-info/requires.txt
btsbots.egg-info/top_level.txt
docs/Makefile
docs/make.bat
docs/source/README
docs/source/conf.py
docs/source/index.rst
docs/source/_static/.gitkeep
tests/test_main.py